disk_tree.py
disk_tree_cli-0.2.0.dist-info/licenses/LICENSE
disk_tree_cli-0.2.0.dist-info/METADATA
disk_tree_cli-0.2.0.dist-info/WHEEL
disk_tree_cli-0.2.0.dist-info/entry_points.txt
disk_tree_cli-0.2.0.dist-info/top_level.txt
disk_tree_cli-0.2.0.dist-info/RECORD
