Metadata-Version: 2.4
Name: disk-tree-cli
Version: 0.2.0
Summary: CLI tool to display disk usage as a color-coded tree
Home-page: https://github.com/your-username/disk-tree-cli
Author: Karan5352
Author-email: you@example.com
Classifier: Programming Language :: Python :: 3
Classifier: License :: OSI Approved :: MIT License
Classifier: Operating System :: OS Independent
Requires-Python: >=3.6
License-File: LICENSE
Requires-Dist: colorama>=0.4.6
Requires-Dist: humanize>=4.9.0
Dynamic: author
Dynamic: author-email
Dynamic: classifier
Dynamic: home-page
Dynamic: license-file
Dynamic: requires-dist
Dynamic: requires-python
Dynamic: summary
